test_iori_add/__init__.py
test_iori_add-0.2.0.dist-info/METADATA
test_iori_add-0.2.0.dist-info/WHEEL
test_iori_add-0.2.0.dist-info/entry_points.txt
test_iori_add-0.2.0.dist-info/RECORD
