Metadata-Version: 2.4
Name: test-iori-add
Version: 0.2.0
Summary: Add your description here
Requires-Python: >=3.13
Requires-Dist: mcp[cli]>=1.11.0
